median_sdk.py
median_sdk-1.6.4.dist-info/licenses/LICENSE
median_sdk-1.6.4.dist-info/METADATA
median_sdk-1.6.4.dist-info/WHEEL
median_sdk-1.6.4.dist-info/entry_points.txt
median_sdk-1.6.4.dist-info/top_level.txt
median_sdk-1.6.4.dist-info/RECORD
