Metadata-Version: 2.4
Name: median-sdk
Version: 1.6.4
Summary: Python SDK for the Median blockchain
Home-page: https://github.com/your-org/median
Author: Median Team
Author-email: Median Team <contact@median.network>
Maintainer-email: Median Team <contact@median.network>
License: Apache-2.0
Project-URL: Homepage, https://github.com/your-org/median
Project-URL: Documentation, https://github.com/your-org/median/blob/main/sdk/python/README.md
Project-URL: Repository, https://github.com/your-org/median
Project-URL: Bug Reports, https://github.com/your-org/median/issues
Project-URL: Changelog, https://github.com/your-org/median/blob/main/sdk/python/CHANGELOG.md
Keywords: blockchain,cosmos,sdk,median,cryptocurrency,crypto,web3
Classifier: Development Status :: 4 - Beta
Classifier: Intended Audience :: Developers
Classifier: Intended Audience :: Financial and Insurance Industry
Classifier: Topic :: Software Development :: Libraries :: Python Modules
Classifier: Topic :: Office/Business :: Financial
Classifier: Topic :: System :: Distributed Computing
Classifier: Programming Language :: Python :: 3
Classifier: Programming Language :: Python :: 3.7
Classifier: Programming Language :: Python :: 3.8
Classifier: Programming Language :: Python :: 3.9
Classifier: Programming Language :: Python :: 3.10
Classifier: Programming Language :: Python :: 3.11
Classifier: Programming Language :: Python :: 3.12
Classifier: Operating System :: OS Independent
Requires-Python: >=3.7
License-File: LICENSE
Requires-Dist: requests>=2.25.0
Provides-Extra: dev
Requires-Dist: twine>=4.0.0; extra == "dev"
Requires-Dist: wheel>=0.37.0; extra == "dev"
Requires-Dist: build>=0.10.0; extra == "dev"
Requires-Dist: pytest>=7.0.0; extra == "dev"
Requires-Dist: pytest-cov>=3.0.0; extra == "dev"
Requires-Dist: black>=22.0.0; extra == "dev"
Requires-Dist: flake8>=4.0.0; extra == "dev"
Requires-Dist: mypy>=0.950; extra == "dev"
Provides-Extra: test
Requires-Dist: pytest>=7.0.0; extra == "test"
Requires-Dist: pytest-cov>=3.0.0; extra == "test"
Requires-Dist: pytest-mock>=3.6.0; extra == "test"
Requires-Dist: responses>=0.20.0; extra == "test"
Dynamic: author
Dynamic: home-page
Dynamic: license-file
Dynamic: requires-python
